auto_aws_mfa/__init__.py
auto_aws_mfa/__main__.py
auto_aws_mfa/mfa.py
auto_aws_mfa/session.py
auto_aws_mfa/util.py
AutoAWSMFA-0.0.4.dist-info/LICENSE
AutoAWSMFA-0.0.4.dist-info/METADATA
AutoAWSMFA-0.0.4.dist-info/WHEEL
AutoAWSMFA-0.0.4.dist-info/entry_points.txt
AutoAWSMFA-0.0.4.dist-info/top_level.txt
AutoAWSMFA-0.0.4.dist-info/RECORD
