Metadata-Version: 2.1
Name: AutoAWSMFA
Version: 0.0.4
Summary: A Python script and library for managing MFA token and AWS Session tokens.
Home-page: https://github.com/pmadhyasta/autoawsmfa
Author: Prashant Madhyasta
Author-email: prashanth.madhyasta@gmail.com
License: AGPLv3
Keywords: AWS,IAM,Security,MFA,AWS Session Token,AWS MFA,autoawsmfa,auto_aws_mfa,AWS MFA,Token
Platform: UNKNOWN
Classifier: Environment :: Console
Classifier: Intended Audience :: Developers
Classifier: Intended Audience :: Information Technology
Classifier: Intended Audience :: System Administrators
Classifier: License :: OSI Approved :: GNU Affero General Public License v3
Classifier: Natural Language :: English
Classifier: Programming Language :: Python :: 3
Classifier: Programming Language :: Python :: 3.5
Classifier: Programming Language :: Python :: 3.6
Classifier: Programming Language :: Python :: 3.7
Classifier: Programming Language :: Python :: 3.8
Classifier: Topic :: Security
Requires-Python: >=3.5, <4
Requires-Dist: botocore
Requires-Dist: packaging
Requires-Dist: python-dateutil
Requires-Dist: boto3
Requires-Dist: keyring
Requires-Dist: pyotp
Requires-Dist: pyperclip
